CHANGELOG.md
LICENSE
trongrid_extractoor/__init__.py
trongrid_extractoor/api.py
trongrid_extractoor/config.py
trongrid_extractoor/helpers/address_helpers.py
trongrid_extractoor/helpers/argument_parser.py
trongrid_extractoor/helpers/csv_helper.py
trongrid_extractoor/helpers/dict_helper.py
trongrid_extractoor/helpers/rich_helpers.py
trongrid_extractoor/helpers/string_constants.py
trongrid_extractoor/helpers/time_helpers.py
trongrid_extractoor/progress_tracker.py
trongrid_extractoor/request_params.py
trongrid_extractoor/response.py
trongrid_extractoor/trc20_txn.py
trongrid_extractor-1.1.0.dist-info/LICENSE
trongrid_extractor-1.1.0.dist-info/METADATA
trongrid_extractor-1.1.0.dist-info/WHEEL
trongrid_extractor-1.1.0.dist-info/entry_points.txt
trongrid_extractor-1.1.0.dist-info/RECORD
